data_preprocessing_lib/__init__.py
data_preprocessing_lib/categorical_encoder.py
data_preprocessing_lib/data_type_converter.py
data_preprocessing_lib/datetime_handler.py
data_preprocessing_lib/feature_engineer.py
data_preprocessing_lib/missing_value_handler.py
data_preprocessing_lib/outlier_handler.py
data_preprocessing_lib/scaler.py
data_preprocessing_lib/text_cleaner.py
data_preprocessing_lib_baragbay/__init__.py
data_preprocessing_lib_baragbay/categorical_encoder.py
data_preprocessing_lib_baragbay/data_type_converter.py
data_preprocessing_lib_baragbay/datetime_handler.py
data_preprocessing_lib_baragbay/feature_engineer.py
data_preprocessing_lib_baragbay/missing_value_handler.py
data_preprocessing_lib_baragbay/outlier_handler.py
data_preprocessing_lib_baragbay/scaler.py
data_preprocessing_lib_baragbay/text_cleaner.py
data_preprocessing_lib_bb/__init__.py
data_preprocessing_lib_bb/categorical_encoder.py
data_preprocessing_lib_bb/data_type_converter.py
data_preprocessing_lib_bb/datetime_handler.py
data_preprocessing_lib_bb/feature_engineer.py
data_preprocessing_lib_bb/missing_value_handler.py
data_preprocessing_lib_bb/outlier_handler.py
data_preprocessing_lib_bb/scaler.py
data_preprocessing_lib_bb/text_cleaner.py
tests/__init__.py
tests/test_categorical_encoder.py
tests/test_data_type_converter.py
tests/test_datetime_handler.py
tests/test_feature_engineer.py
tests/test_missing_value_handler.py
tests/test_outlier_handler.py
tests/test_scaler.py
tests/test_text_cleaner.py
dataprep_lib_bayraker_bar-0.3.dist-info/METADATA
dataprep_lib_bayraker_bar-0.3.dist-info/WHEEL
dataprep_lib_bayraker_bar-0.3.dist-info/top_level.txt
dataprep_lib_bayraker_bar-0.3.dist-info/RECORD
